logus/__init__.py
logus/logcore.py
logus/logparams.py
logus/logtypes.py
logus/settings.py
logus/utils.py
logus-0.0.1.dist-info/LICENSE
logus-0.0.1.dist-info/METADATA
logus-0.0.1.dist-info/WHEEL
logus-0.0.1.dist-info/top_level.txt
logus-0.0.1.dist-info/RECORD
