Metadata-Version: 2.1
Name: logus
Version: 0.0.1
Summary: Static typed structured logging
Author-email: dd84ai <dark.dreamflyer@gmail.com>
License: The MIT License (MIT)
Project-URL: Homepage, https://github.com/darklab8/loguspy
Keywords: logging,structured,typing
Classifier: License :: OSI Approved :: MIT License
Classifier: Programming Language :: Python
Classifier: Programming Language :: Python :: 3
Requires-Python: >=3.8
License-File: LICENSE
Provides-Extra: dev
Requires-Dist: black ; extra == 'dev'
Requires-Dist: flake8 ; extra == 'dev'
Requires-Dist: isort ; extra == 'dev'
Requires-Dist: autoflake ; extra == 'dev'
Requires-Dist: mypy ; extra == 'dev'
